mcp_server_deepresearch_deepseek_liu/__init__.py
mcp_server_deepresearch_deepseek_liu/__main__.py
mcp_server_deepresearch_deepseek_liu/server.py
mcp_server_deepresearch_deepseek_liu-0.1.2.dist-info/METADATA
mcp_server_deepresearch_deepseek_liu-0.1.2.dist-info/WHEEL
mcp_server_deepresearch_deepseek_liu-0.1.2.dist-info/entry_points.txt
mcp_server_deepresearch_deepseek_liu-0.1.2.dist-info/top_level.txt
mcp_server_deepresearch_deepseek_liu-0.1.2.dist-info/RECORD
